{
  "A": "/æɪ/",
  "ABILITY": "/əˈ.bɪl.ɪ.ti/",
  "ABLE": "/ˈeɪ.bl̩/",
  "ABOUT": "/əˈbɛʊt/",
  "ABSTAIN": "/əbˈsteɪn/",
  "ACCEPT": "/ækˈsɛpt/",
  "ACCEPTANCE": "/ək.ˈsɛp.təns/",
  "ACCEPTED": "/æk.ˈsɛp.tɪd/",
  "ACCOUNT": "/ə.ˈkaʊnt/",
  "ACCOUNTABLE": "/ə.ˈkaʊn.tə.bəl/",
  "ACCUSE": "/əˈkjuːz/",
  "ACHIEVED": "/əˈtʃiːvd/",
  "ACROSS": "/əˈkɹɑs/",
  "ACT": "/æk/",
  "ACTING": "/ˈæk.tɪŋ/",
  "ALSO": "/ˈɔːl.səʊ/",
  "AMIGO": "/əˈmiː.ɡəʊ/",
  "AMOUNT": "/əˈmaʊnt/",
  "AMUSEMENT": "/əˈmjuzmənt/",
  "AN": "/æn/",
  "ANALYZE": "/ˈæn.ə.laɪz/",
  "ANCIENT": "/ˈeɪn.ʃənt/",
  "ANIMAL": "/ˈænɪməl/",
  "ANIMALS": "/ˈæn.ɪ.məlz/",
  "ANYTHING": "/ˈɛ.nə.θɪŋ/",
  "APP": "[ʔæʔp̚]",
  "APPEARING": "/əˈpɪəɹ.ɪŋ/",
  "APPLE": "/ˈæp.əl/",
  "ATTENTION": "/əˈtɛn.ʃən/",
  "AUTHORITY": "/ɔːˈθɒɹəti/",
  "AVOID": "/əˈvɔɪd/",
  "BAD": "/bæːd/",
  "BADLY": "/ˈbæd.li/",
  "BAG": "/ˈbæːɡ/",
  "BAKED": "/beɪkt/",
  "BARS": "/ˈbɑː(ɹ)z/",
  "BASE": "/beɪs/",
  "BASED": "/beɪst/",
  "BATTLE": "/ˈbætəl/",
  "BETTER": "[ˈbeɾə]",
  "BETWEEN": "/bɪˈtwiːn/",
  "BEYOND": "/biˈjɒnd/",
  "BIG": "/bɪɡ/",
  "BIOLOGY": "/baɪˈɒlədʒɪ/",
  "BIRD": "/bɜd/",
  "BITE": "/bʌɪt/",
  "BLAZE": "/bleɪz/",
  "BLEND": "/blɛnd/",
  "BLOOD": "/blʊd/",
  "BLUE": "/bluː/",
  "BOARD": "/bɔːd/",
  "BOAT": "/bəʊt/",
  "BODILY": "/ˈbɒdɪli/",
  "BUILDING": "/ˈbɪl.dɪŋ/",
  "BUILDINGS": "/ˈbɪldɪŋz/",
  "BULBOUS": "/ˈboʊlbəs/",
  "BUSINESS": "/ˈbɪd.nəs/",
  "BUT": "/bʊt/",
  "BUY": "/baɪ/",
  "BY": "/baɪ/",
  "CAKE": "/keɪk/",
  "CALF": "/kæf/",
  "CALLING": "/ˈkɔːlɪŋ/",
  "CAMERA": "/ˈkæməɹə/",
  "CANCEROUS": "/kænsəɹəs/",
  "CENTRAL": "/ˈsɛntɹəl/",
  "CEREMONY": "/ˈsɛɹɪməni/",
  "CERTAIN": "/ˈsɝtn̩/",
  "CHANGE": "/tʃeɪndʒ/",
  "CHART": "/tʃɑːt/",
  "CHEEK": "/tʃiːk/",
  "CHEESY": "/ˈtʃiːzi/",
  "CHEMISTRY": "/ˈkɛm.ɪ.stɹi/",
  "CHEST": "/t͡ʃɛst/",
  "CHEW": "/tʃuː/",
  "CHILI": "/ˈt͡ʃɪli/",
  "CHOCOLATE": "/ˈt͡ʃɔk(ə)lət/",
  "COARSE": "/kɔːs/",
  "COATING": "/ˈkəʊtɪŋ/",
  "COFFEE": "/ˈkɑ.fi/",
  "COLD": "/kɔʊld/",
  "COLLECTIVE": "/kəˈlɛktɪv/",
  "COLOR": "/ˈkʌl.ə(ɹ)/",
  "COMMERCIAL": "/kəˈmɜːʃəl/",
  "COMMON": "/ˈkɒmən/",
  "COMMUNICATION": "/kəˌmjuːnɪˈkeɪʃən/",
  "COMMUNITY": "/k(ə)ˈmjunəti/",
  "COMPANY": "/ˈkʌmp(ə)ni/",
  "COMPLETE": "/kəmˈpliːt/",
  "CORRECTLY": "/kəˈɹɛktli/",
  "CORRESPONDENCE": "/ˌkɒɹɪˈspɒndəns/",
  "COUNTERPART": "/ˈkaʊntəˌpɑːt/",
  "COUNTRIES": "/ˈkʌntɹiz/",
  "COUNTRY": "/ˈkɐntɹi/",
  "COURSE": "/kɔːs/",
  "COVER": "/ˈkʌvə/",
  "COW": "/kaʊ/",
  "CRABS": "/kɹæbz/",
  "CRACKED": "/kɹækt/",
  "CRAZY": "/ˈkɹeɪzi/",
  "CREDENTIAL": "/kɹɪˈdɛnʃəl/",
  "CRIME": "/kɹaɪm/",
  "CROSS": "/kɹɑs/",
  "CUBE": "/kjuːb/",
  "DEEP": "/diːp/",
  "DEFINITE": "/ˈdɛfɪnɪt/",
  "DELIBERATELY": "/dəˈlɪb(ə)ɹətli/",
  "DELICATE": "/ˈdɛlɪkət/",
  "DENTAL": "/ˈdɛntl̩/",
  "DESERT": "/dɪˈzɜːt/",
  "DESIRED": "/dɪˈzaɪəd/",
  "DESPITE": "/dɪˈspaɪt/",
  "DETAIL": "/ˈdiːteɪl/",
  "DETAILED": "/dɪˈteɪld/",
  "DEVICE": "/dəˈvaɪs/",
  "DEVOID": "/dɪˈvɔɪd/",
  "DIFFERENT": "/ˈdɪf.(ə)ɹ.ənt/",
  "DOING": "/ˈduːɪŋ/",
  "DOOR": "/dɔː/",
  "DOUBT": "/dʌʊt/",
  "DRAMATIC": "/dɹəˈmætɪk/",
  "DRAWERS": "/dɹɔːz/",
  "DRAWINGS": "/ˈdɹɑ.ɪŋz/",
  "DRINK": "/dɹɪŋk/",
  "DRIVEN": "/ˈdɹɪvən/",
  "DUMMY": "/ˈdʌmi/",
  "DUST": "/dʌst/"
}
